histopy/__init__.py
histopy/hp.py
histopy-0.6.2.dist-info/DESCRIPTION.rst
histopy-0.6.2.dist-info/METADATA
histopy-0.6.2.dist-info/RECORD
histopy-0.6.2.dist-info/WHEEL
histopy-0.6.2.dist-info/metadata.json
histopy-0.6.2.dist-info/top_level.txt
history/__init__.py
history/history.py
