Metadata-Version: 2.0
Name: histopy
Version: 0.6.2
Summary: Bash-style history for Python interactive interpreter
Home-page: https://github.com/dwpaley/histopy
Author: Daniel W. Paley
Author-email: dwpaley@gmail.com
License: UNKNOWN
Platform: UNKNOWN
Classifier: Programming Language :: Python :: 3
Classifier: License :: OSI Approved :: MIT License
Classifier: Operating System :: OS Independent
